hapiutils.py
hapiutils-0.1.dist-info/LICENSE
hapiutils-0.1.dist-info/METADATA
hapiutils-0.1.dist-info/WHEEL
hapiutils-0.1.dist-info/top_level.txt
hapiutils-0.1.dist-info/RECORD
