Metadata-Version: 2.1
Name: hapiutils
Version: 0.1
Summary: Additional hapiclient tools including merge, etc
Author-email: Johns Hopkins University Applied Physics Laboratory LLC <sandy.antunes@jhuapl.edu>
License: BSD-3-Clause
Project-URL: Homepage, https://hapi-server.org
Project-URL: Documentation, https://github.com/hapi-server/tools-python
Project-URL: Repository, https://github.com/hapi-server/tools-python
Keywords: HAPI
Classifier: Development Status :: 3 - Alpha
Classifier: Topic :: Utilities
Requires-Python: >=3.9
License-File: LICENSE
Requires-Dist: numpy
Requires-Dist: pandas
